gym_hil/__init__.py
gym_hil/assets/arrange_boxes_scene.xml
gym_hil/assets/franka_emika_panda/meshes/link0.stl
gym_hil/assets/franka_emika_panda/meshes/link0_0.obj
gym_hil/assets/franka_emika_panda/meshes/link0_1.obj
gym_hil/assets/franka_emika_panda/meshes/link0_10.obj
gym_hil/assets/franka_emika_panda/meshes/link0_11.obj
gym_hil/assets/franka_emika_panda/meshes/link0_2.obj
gym_hil/assets/franka_emika_panda/meshes/link0_3.obj
gym_hil/assets/franka_emika_panda/meshes/link0_4.obj
gym_hil/assets/franka_emika_panda/meshes/link0_5.obj
gym_hil/assets/franka_emika_panda/meshes/link0_7.obj
gym_hil/assets/franka_emika_panda/meshes/link0_8.obj
gym_hil/assets/franka_emika_panda/meshes/link0_9.obj
gym_hil/assets/franka_emika_panda/meshes/link1.obj
gym_hil/assets/franka_emika_panda/meshes/link1.stl
gym_hil/assets/franka_emika_panda/meshes/link2.obj
gym_hil/assets/franka_emika_panda/meshes/link2.stl
gym_hil/assets/franka_emika_panda/meshes/link3.stl
gym_hil/assets/franka_emika_panda/meshes/link3_0.obj
gym_hil/assets/franka_emika_panda/meshes/link3_1.obj
gym_hil/assets/franka_emika_panda/meshes/link3_2.obj
gym_hil/assets/franka_emika_panda/meshes/link3_3.obj
gym_hil/assets/franka_emika_panda/meshes/link4.stl
gym_hil/assets/franka_emika_panda/meshes/link4_0.obj
gym_hil/assets/franka_emika_panda/meshes/link4_1.obj
gym_hil/assets/franka_emika_panda/meshes/link4_2.obj
gym_hil/assets/franka_emika_panda/meshes/link4_3.obj
gym_hil/assets/franka_emika_panda/meshes/link5_0.obj
gym_hil/assets/franka_emika_panda/meshes/link5_1.obj
gym_hil/assets/franka_emika_panda/meshes/link5_2.obj
gym_hil/assets/franka_emika_panda/meshes/link5_collision_0.obj
gym_hil/assets/franka_emika_panda/meshes/link5_collision_1.obj
gym_hil/assets/franka_emika_panda/meshes/link5_collision_2.obj
gym_hil/assets/franka_emika_panda/meshes/link6.stl
gym_hil/assets/franka_emika_panda/meshes/link6_0.obj
gym_hil/assets/franka_emika_panda/meshes/link6_1.obj
gym_hil/assets/franka_emika_panda/meshes/link6_10.obj
gym_hil-0.1.13.dist-info/METADATA
gym_hil-0.1.13.dist-info/WHEEL
gym_hil-0.1.13.dist-info/licenses/LICENSE
gym_hil-0.1.13.dist-info/RECORD
