Metadata-Version: 2.4
Name: gym-hil
Version: 0.1.13
Summary: A gymnasium environment for Human-in-the-Loop Reinforcement Learning
License: Apache-2.0
License-File: LICENSE
Author: Khalil Meftah
Author-email: kmeftah.khalil@gmail.com
Requires-Python: >=3.10
Classifier: Development Status :: 3 - Alpha
Classifier: Intended Audience :: Developers
Classifier: Topic :: Software Development :: Build Tools
Classifier: License :: OSI Approved :: Apache Software License
Classifier: Programming Language :: Python :: 3.10
Provides-Extra: dev
Provides-Extra: test
Requires-Dist: debugpy (>=1.8.1) ; extra == "dev"
Requires-Dist: gymnasium (>=0.29.1,<2.0.0)
Requires-Dist: hidapi (>=0.14.0)
Requires-Dist: imageio[ffmpeg] (>=2.34.0)
Requires-Dist: mujoco (>=2.3.7,<4.0.0)
Requires-Dist: pre-commit (>=3.7.0) ; extra == "dev"
Requires-Dist: pygame (>=2.5.1)
Requires-Dist: pynput (>=1.7.7)
Requires-Dist: pytest (>=8.1.0) ; extra == "test"
Requires-Dist: pytest-cov (>=5.0.0) ; extra == "test"
Project-URL: Homepage, https://github.com/huggingface/gym-hil
Project-URL: issues, https://github.com/huggingface/gym-hil/issues
